LICENSE
MANIFEST.in
README.md
setup.cfg
setup.py
byu_ws_sdk/__init__.py
byu_ws_sdk/core.py
byu_ws_sdk/demo.py
byu_ws_sdk.egg-info/PKG-INFO
byu_ws_sdk.egg-info/SOURCES.txt
byu_ws_sdk.egg-info/dependency_links.txt
byu_ws_sdk.egg-info/requires.txt
byu_ws_sdk.egg-info/top_level.txt
byu_ws_sdk.egg-info/zip-safe
byu_ws_sdk/test/__init__.py
byu_ws_sdk/test/test_byu_ws_sdk.py
byu_ws_sdk/test/test_byu_ws_sdk_with_input.py