Metadata-Version: 1.0
Name: byu-ws-sdk
Version: 0.10.0
Summary: A Python SDK for calling BYU REST web services.
Home-page: https://github.com/byu-oit-core-appeng/byu-ws-sdk-python
Author: BYU OIT Core Application Engineering
Author-email: paul_eden@byu.edu
License: MIT
Platform: UNKNOWN
